InstagramLive/__init__.py
InstagramLive/main.py
InstagramLive-0.0.1.dist-info/METADATA
InstagramLive-0.0.1.dist-info/WHEEL
InstagramLive-0.0.1.dist-info/top_level.txt
InstagramLive-0.0.1.dist-info/RECORD
